asdm/__init__.py
asdm/asdm.py
asdm/cli.py
asdm/utilities.py
asdm/Inference/MCMC.py
asdm/Inference/Optimizer.py
asdm/Inference/Payoff.py
asdm/Inference/Probability.py
asdm/Inference/__init__.py
asdm/simulator/__init__.py
asdm/simulator/__main__.py
asdm/simulator/app.py
asdm/simulator/static/css/main.css
asdm/simulator/static/js/main.js
asdm/simulator/templates/index.html
asdm-0.7.0.dist-info/licenses/LICENSE
asdm-0.7.0.dist-info/METADATA
asdm-0.7.0.dist-info/WHEEL
asdm-0.7.0.dist-info/entry_points.txt
asdm-0.7.0.dist-info/top_level.txt
asdm-0.7.0.dist-info/RECORD
