Metadata-Version: 2.4
Name: asdm
Version: 0.7.0
Summary: A Python package for System Dynamics Modeling
Author: Matt Stammers
Author-email: Wang Zhao <wzh1895@outlook.com>
License: MIT
Project-URL: Homepage, https://github.com/wzh1895/ASDM
Project-URL: Source Code, https://github.com/wzh1895/ASDM
Project-URL: Matt Stammers's GitHub, https://github.com/MattStammers
Classifier: Programming Language :: Python :: 3
Classifier: License :: OSI Approved :: MIT License
Classifier: Operating System :: OS Independent
Requires-Python: >=3.9
License-File: LICENSE
Requires-Dist: numpy
Requires-Dist: pandas
Requires-Dist: matplotlib
Requires-Dist: networkx
Requires-Dist: lxml
Requires-Dist: beautifulsoup4
Requires-Dist: scipy
Requires-Dist: Flask
Dynamic: license-file
